mhclovac/__init__.py
mhclovac/config.py
mhclovac/models.py
mhclovac/preprocessing.py
mhclovac/run.py
mhclovac/sequence.py
mhclovac/training.py
mhclovac/utils.py
mhclovac/index/index_data.gz
mhclovac/models/BoLA-1*21:01.model.gz
mhclovac/models/BoLA-1*23:01.model.gz
mhclovac/models/BoLA-2*08:01.model.gz
mhclovac/models/BoLA-2*12:01.model.gz
mhclovac/models/BoLA-3*01:01.model.gz
mhclovac/models/BoLA-3*02:01.model.gz
mhclovac/models/BoLA-4*24:01.model.gz
mhclovac/models/BoLA-6*13:01.model.gz
mhclovac/models/BoLA-6*13:02.model.gz
mhclovac/models/BoLA-6*41:01.model.gz
mhclovac/models/Gogo-B*01:01.model.gz
mhclovac/models/H-2-Db.model.gz
mhclovac/models/H-2-Dd.model.gz
mhclovac/models/H-2-Dq.model.gz
mhclovac/models/H-2-Kb.model.gz
mhclovac/models/H-2-Kd.model.gz
mhclovac/models/H-2-Kk.model.gz
mhclovac/models/H-2-Kq.model.gz
mhclovac/models/H-2-Ld.model.gz
mhclovac/models/H-2-Lq.model.gz
mhclovac/models/HLA-A*01:01.model.gz
mhclovac/models/HLA-A*01:03.model.gz
mhclovac/models/HLA-A*02:01.model.gz
mhclovac/models/HLA-A*02:02.model.gz
mhclovac/models/HLA-A*02:03.model.gz
mhclovac/models/HLA-A*02:04.model.gz
mhclovac/models/HLA-A*02:05.model.gz
mhclovac/models/HLA-A*02:06.model.gz
mhclovac/models/HLA-A*02:07.model.gz
mhclovac/models/HLA-A*02:10.model.gz
mhclovac/models/HLA-A*02:11.model.gz
mhclovac/models/HLA-A*02:12.model.gz
mhclovac/models/HLA-A*02:14.model.gz
mhclovac/models/HLA-A*02:16.model.gz
mhclovac/models/HLA-A*02:17.model.gz
mhclovac/models/HLA-A*02:19.model.gz
mhclovac/models/HLA-A*02:50.model.gz
mhclovac/models/HLA-A*03:01.model.gz
mhclovac/models/HLA-A*03:02.model.gz
mhclovac/models/HLA-A*03:19.model.gz
mhclovac/models/HLA-A*11:01.model.gz
mhclovac/models/HLA-A*11:02.model.gz
mhclovac/models/HLA-A*23:01.model.gz
mhclovac/models/HLA-A*24:02.model.gz
mhclovac/models/HLA-A*24:03.model.gz
mhclovac/models/HLA-A*24:06.model.gz
mhclovac/models/HLA-A*24:13.model.gz
mhclovac/models/HLA-A*25:01.model.gz
mhclovac/models/HLA-A*26:01.model.gz
mhclovac-4.0.dist-info/LICENSE
mhclovac-4.0.dist-info/METADATA
mhclovac-4.0.dist-info/WHEEL
mhclovac-4.0.dist-info/entry_points.txt
mhclovac-4.0.dist-info/top_level.txt
mhclovac-4.0.dist-info/RECORD
