Metadata-Version: 2.1
Name: mhclovac
Version: 4.0
Summary: MHC binding prediction based on modeled physicochemical properties of peptides
Home-page: https://github.com/stefs304/mhclovac
Author: Stefan Stojanovic
Author-email: stefs304@gmail.com
License: UNKNOWN
Platform: UNKNOWN
Classifier: Programming Language :: Python :: 3.8
Classifier: License :: OSI Approved :: MIT License
Classifier: Intended Audience :: Science/Research
Classifier: Topic :: Scientific/Engineering :: Bio-Informatics
Classifier: Operating System :: POSIX :: Linux
Requires-Dist: scikit-learn (==0.23.2)
Requires-Dist: numpy
Requires-Dist: pandas
Requires-Dist: joblib
Requires-Dist: argparse
Requires-Dist: pandarallel
